render_engine_aggregators/feed.py
render_engine_aggregators-2023.6.1.dist-info/METADATA
render_engine_aggregators-2023.6.1.dist-info/WHEEL
render_engine_aggregators-2023.6.1.dist-info/top_level.txt
render_engine_aggregators-2023.6.1.dist-info/RECORD
