Metadata-Version: 2.1
Name: render-engine-aggregators
Version: 2023.6.1
Summary: aggregate multiple collections
Requires-Dist: render-engine (>=2023.6.1)
Provides-Extra: dev
Requires-Dist: pytest ; extra == 'dev'
Requires-Dist: ruff ; extra == 'dev'
Requires-Dist: black ; extra == 'dev'
